scrit/__init__.py
scrit/app.py
scrit/audio.py
scrit/config.py
scrit/listener.py
scrit/settings.json
scrit-0.0.1.dist-info/LICENSE
scrit-0.0.1.dist-info/METADATA
scrit-0.0.1.dist-info/WHEEL
scrit-0.0.1.dist-info/entry_points.txt
scrit-0.0.1.dist-info/top_level.txt
scrit-0.0.1.dist-info/RECORD
