Metadata-Version: 2.1
Name: scrit
Version: 0.0.1
Summary: command line tool to manage transcription of system audio with openai whisper
Author-email: Joseph Courtney <joseph.m.courtney@gmail.com>
Project-URL: Homepage, https://github.com/josephcourtney/scrit
Classifier: Development Status :: 3 - Alpha
Classifier: License :: OSI Approved :: MIT License
Classifier: Programming Language :: Python :: 3
Requires-Python: >=3.9
License-File: LICENSE
Requires-Dist: PyAudio (>=0.2.13)
Requires-Dist: openai-whisper (>=20230314)
Requires-Dist: SpeechRecognition (>=3.10.0)
Requires-Dist: torch (>=2.0.1)
Requires-Dist: pyperclip (>=1.8.2)
Requires-Dist: rich (>=13.4.2)
